pretrained_models/__init__.py
pretrained_models-0.0.0.dist-info/WHEEL
pretrained_models-0.0.0.dist-info/METADATA
pretrained_models-0.0.0.dist-info/RECORD
