Metadata-Version: 2.1
Name: pretrained-models
Version: 0.0.0
Summary: Pre-trained models.
Author: Yevgnen Koh
Author-email: wherejoystarts@gmail.com
Requires-Python: >=3.8,<4.0
Classifier: Programming Language :: Python :: 3
Classifier: Programming Language :: Python :: 3.8
Classifier: Programming Language :: Python :: 3.9
